CHANGES.txt
MANIFEST.in
README.txt
setup.py
buildout/__init__.py
buildout.recipe.isolation.egg-info/PKG-INFO
buildout.recipe.isolation.egg-info/SOURCES.txt
buildout.recipe.isolation.egg-info/dependency_links.txt
buildout.recipe.isolation.egg-info/entry_points.txt
buildout.recipe.isolation.egg-info/namespace_packages.txt
buildout.recipe.isolation.egg-info/not-zip-safe
buildout.recipe.isolation.egg-info/requires.txt
buildout.recipe.isolation.egg-info/top_level.txt
buildout/recipe/__init__.py
buildout/recipe/isolation/README.rst
buildout/recipe/isolation/__init__.py
buildout/recipe/isolation/isolation.py
buildout/recipe/isolation/tests.py
buildout/recipe/isolation/utils.py