Metadata-Version: 1.0
Name: buildout.recipe.isolation
Version: 0.2.0
Summary: Recipe for isolating Python distributions (packages and scripts).
Home-page: http://weblion.psu.edu/trac/weblion/browser/weblion/buildout.recipe.isolation
Author: Michael Mulich | WebLion Group, Penn State University
Author-email: support@weblion.psu.edu
License: GPL 2
Keywords: development build
Platform: UNKNOWN
Classifier: Framework :: Buildout
Classifier: Intended Audience :: Developers
Classifier: License :: OSI Approved :: Zope Public License
Classifier: Topic :: Software Development :: Build Tools
Classifier: Topic :: Software Development :: Libraries :: Python Modules
Classifier: Development Status :: 4 - Beta
